embedding_server_client/__init__.py
embedding_server_client/async_client.py
embedding_server_client/client.py
embedding_server_client/error.py
embedding_server_client/schema/__init__.py
embedding_server_client/schema/base.py
embedding_server_client/schema/document.py
embedding_server_client/schema/document_status.py
embedding_server_client/schema/embedding.py
embedding_server_client/schema/health_check.py
embedding_server_client/schema/split.py
embedding_server_client/schema/summary.py
embedding_server_client/schema/zmq_message_header.py
embedding_server_client/tests/__init__.py
embedding_server_client/tests/client_integration_superlinear.py
embedding_server_client/tests/client_integration_tests.py
embedding_server_client/tests/multilingual_tests.py
embedding_server_client/tests/test_base.py
embedding_server_client/tests/test_client.py
embedding_server_client/tests/test_msgpack.py
embedding_server_client/tests/test_zmq_message_header.py
embedding_server_client-1.0.5.dist-info/METADATA
embedding_server_client-1.0.5.dist-info/WHEEL
embedding_server_client-1.0.5.dist-info/top_level.txt
embedding_server_client-1.0.5.dist-info/RECORD
